gitlab_events-0.0.3.data/scripts/gitlab-events
gitlabevents/__init__.py
gitlabevents/args.py
gitlabevents/log.py
gitlabevents/main.py
gitlab_events-0.0.3.dist-info/LICENSE
gitlab_events-0.0.3.dist-info/METADATA
gitlab_events-0.0.3.dist-info/WHEEL
gitlab_events-0.0.3.dist-info/top_level.txt
gitlab_events-0.0.3.dist-info/RECORD
