Metadata-Version: 2.1
Name: gitlab-events
Version: 0.0.3
Summary: Gitlab events to CSV table
Home-page: https://github.com/Iheiko/gitlab-events/
Author: Viktor Prymak
Author-email: sammorow@gmail.com
License: UNKNOWN
Platform: UNKNOWN
Classifier: Programming Language :: Python :: 3
Classifier: Topic :: Education
Classifier: Environment :: Console
Classifier: License :: OSI Approved :: MIT License
Classifier: Operating System :: OS Independent
Requires-Dist: termcolor
Requires-Dist: colorama
Requires-Dist: python-gitlab
